steganosaurus/__init__.py
steganosaurus/constants.py
steganosaurus/fernet_cryptor.py
steganosaurus/hash_utils.py
steganosaurus/otp_cryptor.py
steganosaurus/picture_modifier.py
steganosaurus/steganography.py
steganosaurus-1.0.1.dist-info/LICENSE.txt
steganosaurus-1.0.1.dist-info/METADATA
steganosaurus-1.0.1.dist-info/WHEEL
steganosaurus-1.0.1.dist-info/top_level.txt
steganosaurus-1.0.1.dist-info/RECORD
