Metadata-Version: 2.1
Name: steganosaurus
Version: 1.0.1
Summary: Hide data into image file
Home-page: https://github.com/duongntbk/steganosaurus
Author: Nguyen Thai Duong
Author-email: duongnt.bk@gmail.com
License: UNKNOWN
Platform: UNKNOWN
Classifier: Programming Language :: Python :: 3
Classifier: License :: OSI Approved :: MIT License
Classifier: Operating System :: OS Independent
Requires-Dist: cryptography (>=2.3.1)
Requires-Dist: bitarray (>=0.8.3)
Requires-Dist: Pillow (>=5.3.0)
Requires-Dist: bcrypt (>=3.1.4)
